all_page_login
all_page_login_test
