Metadata-Version: 1.0
Name: all-page-login
Version: 0.1.1
Summary: All Page Login 
Home-page: UNKNOWN
Author: Jacek Bzdak
Author-email: jacek@askesis.pl
License: MIT
Platform: UNKNOWN
